{
    "_links": {
        "self": {
            "href": "http:\/\/default\/sites\/default\/files\/inline-images\/sitronics.png"
        },
        "type": {
            "href": "http:\/\/drupal.org\/rest\/type\/file\/file"
        },
        "http:\/\/drupal.org\/rest\/relation\/file\/file\/uid": [
            {
                "href": "http:\/\/default\/user\/1?_format=hal_json"
            }
        ]
    },
    "uuid": [
        {
            "value": "8b4dda07-ec78-4af5-94e3-3377ff77ea51"
        }
    ],
    "langcode": [
        {
            "value": "uk"
        }
    ],
    "_embedded": {
        "http:\/\/drupal.org\/rest\/relation\/file\/file\/uid": [
            {
                "_links": {
                    "self": {
                        "href": "http:\/\/default\/user\/1?_format=hal_json"
                    },
                    "type": {
                        "href": "http:\/\/drupal.org\/rest\/type\/user\/user"
                    }
                },
                "uuid": [
                    {
                        "value": "309373d7-bbdc-4043-ad0f-45d9a3b98abf"
                    }
                ]
            }
        ]
    },
    "filename": [
        {
            "value": "sitronics.png"
        }
    ],
    "uri": [
        {
            "value": "public:\/\/inline-images\/sitronics.png",
            "url": "\/sites\/default\/files\/inline-images\/sitronics.png"
        }
    ],
    "filemime": [
        {
            "value": "image\/png"
        }
    ],
    "filesize": [
        {
            "value": 1211
        }
    ],
    "status": [
        {
            "value": true
        }
    ],
    "created": [
        {
            "value": "2020-04-20T18:37:55+00:00",
            "format": "Y-m-d\\TH:i:sP"
        }
    ],
    "changed": [
        {
            "value": "2020-04-20T18:40:59+00:00",
            "format": "Y-m-d\\TH:i:sP"
        }
    ]
}